{
    "help": {
        "name": "help",
        "description": "List of all bot commands!",
        "buttonText": "Help"
    },
    "class": {
        "name": "class",
        "description": "Information about the available classes.",
        "options": [
            {
                "name": "class",
                "description": "Information about a specific class."
            }
        ],
        "buttonText": "Classes"
    },
    "liquidmemories": {
        "name": "liquidmemories",
        "description": "Information about the available Liquid Memories.",
        "options": [
            {
                "name": "color",
                "description": "Information about a specific liquid memory."
            }
        ],
        "buttonText": "Liquid Memories"
    },
    "imagine": {
        "name": "imagine",
        "description": "Information about all available Imagine.",
        "buttonText": "Imagine"
    }
}